python_rclone_wrapper/__init__.py
python_rclone_wrapper/cli.py
python_rclone_wrapper/locking.py
python_rclone_wrapper/rclone.py
python_rclone_wrapper-0.4.0.dist-info/METADATA
python_rclone_wrapper-0.4.0.dist-info/WHEEL
python_rclone_wrapper-0.4.0.dist-info/entry_points.txt
python_rclone_wrapper-0.4.0.dist-info/top_level.txt
python_rclone_wrapper-0.4.0.dist-info/RECORD
