Metadata-Version: 2.1
Name: python-rclone-wrapper
Version: 0.4.0
Summary: Python RClone Wrapper
Home-page: https://github.com/ahmedbodi/python_rclone_wrapper
Author: Ahmed Bodiwala
Author-email: ahmedbodi@crypto-expert.com
License: UNKNOWN
Keywords: python_rclone_wrapper
Platform: UNKNOWN
Classifier: Development Status :: 2 - Pre-Alpha
Classifier: Intended Audience :: Developers
Classifier: Natural Language :: English
Classifier: Programming Language :: Python :: 2.7
Classifier: Programming Language :: Python :: 3
Classifier: Programming Language :: Python :: 3.5
Classifier: Programming Language :: Python :: 3.6
Classifier: Programming Language :: Python :: 3.7
Classifier: Programming Language :: Python :: 3.8
Requires-Python: >=2.7
